Workbook

Sheet COSTES_FIJOS
B2: COSTES DE PERSONAL | C2: DATOS MENSUALES | D2: TOTALES AÑO
B3: Salario socio 1/ media jornada | C3: 300 | D3: =C3*12 -> 3600
B4: Salario socio 2/ media jornada | C4: 300 | D4: =C4*12 -> 3600
B5: Salario socio 3/ media jornada | C5: 300 | D5: =C5*12 -> 3600
B6: Salario socio 4/ media jornada | C6: 300 | D6: =C6*12 -> 3600
B7: Total salarios socios | D7: =SUM(C3:C6)*12 -> 14400
B8: Coste autónomos (tarifa plana) | C8: =80*4 -> 320 | D8: =C8*12 -> 3840
B9: TOTAL GASTOS DE PERSONAL | D9: =D7+D8 -> 18240
B12: OTROS COSTES | C12: DATOS MENSUALES | D12: TOTALES AÑO
B13: AWS | C13: 50 | D13: =C13*12 -> 600
B14: Gestoría de autónomos | C14: 70 | D14: =C14*12 -> 840
B15: Mantenimiento | C15: 30 | D15: =C15*12 -> 360
B16: OTROS COSTES | C16: 50 | D16: =C16*12 -> 600
B18: TOTAL OTROS COSTES | C18: =SUM(C13:C16) -> 200 | D18: =SUM(D13:D17) -> 2400
B20: TOTAL COSTES FIJOS (personal + otros costes) | D20: =D9+D18 -> 20640

Sheet COSTES_VARIABLES
B3: PRODUCTO / SERVICIO | C3: UNIDADES | D3: COSTE/PRECIO/ medio unidad | E3: DATOS MENSUALES
B4: Comisión Pasarela (Stripe) | C4: 1 | D4: 1 | E4: =C4*D4 -> 1
B5: Publicidad/Captación (Ads) | C5: 1 | D5: 4 | E5: =C4*D5 -> 4
B6: Soporte/Servidor extra | C6: 1 | D6: 0.5 | E6: =C4*D6 -> 0.5
B8: TOTAL COSTES VARIABLES PRODUCTO 1 | E8: =SUM(E4:E7) -> 5.5
B9: TOTAL COSTES VARIABLES | E9: =E8 -> 5.5

Sheet GASTOS_DE_PUESTA_EN_MARCHA
B4: GASTOS INICIALES O DE CONSITUCIÓN | C4: IMPORTE
B5: Notaría | C5: 150
B6: Honorarios Asesor/Gestoría | C6: 125
B7: Registro mercantil | C7: 0
B9: TOTALES GASTOS INICIALES | C9: =SUM(C5:C8) -> 275
B11: GASTOS DE LANZAMIENTO | C11: IMPORTE
B12: Desarrollo de página web | C12: 0
B13: Diseño de marca / Logo | C13: 0
B14: Campaña de lanzamiento | C14: 300
B16: TOTALES GASTOS DE LANZAMIENTO | C16: =SUM(C12:C15) -> 300
B19: GASTOS TOTAL DE PUESTA EN MARCHA | C19: =C9+C16 -> 575

Sheet INVERSIÓN_EN_INMOVILIZADO
B4: COMPRAS DE INMOVILIZADO | C4: IMPORTE | D4: Nº DE AÑOS | E4: DOTACIÓN AMORTIZACIÓN ANUAL | F4: DOTACIÓN AMORTIZACIÓN MENSUAL
C5: 0 | D5: 0 | E5: 0 | F5: =E5/12 -> 0
B7: TOTALES | C7: =SUM(C5:C6) -> 0 | E7: =SUM(E5:E6) -> 0 | F7: =SUM(F5:F6) -> 0

Sheet PLAN_DE_INVERSIÓN_FINANCIACIÓN
B5: COSTE / GASTO / INVERSIÓN | C5: GASTO ÚNICO | D5: GASTO EN 4 MESES
B7: COSTES FIJOS | D7: =COSTES_FIJOS!D20/12*4 -> 6880
B8: COSTES VARIABLES | D8: =COSTES_VARIABLES!E9/12*4 -> 1.8333333
B9: GASTOS DE PUESTA EN MARCHA | C9: =GASTOS_DE_PUESTA_EN_MARCHA!C16 -> 300
B10: INMOVILIZADO | C10: ='INVERSIÓN_EN_INMOVILIZADO'!C7 -> 0
B12: TOTALES | C12: =SUM(C7:C10) -> 300 | D12: =SUM(D7:D10) -> 6881.8333
B14: TOTAL INVERSIÓN NECESARIA | D14: =C12+D12 -> 7181.8333
B17: FINANCIACIÓN
B18: RECURSOS PROPIOS | C18: 1 | D18: =D14*C18 -> 7181.8333
B20: TOTAL FINANCIACIÓN | D20: =SUM(D18) -> 7181.8333

Sheet INGRESOS
D2: AÑO 1 | S2: AÑO 2
C3: VENTAS E INGRESOS | D3: MES 1 | E3: MES 2 | F3: MES 3 | G3: MES 4 | H3: MES 5 | I3: MES 6 | J3: MES 7 | K3: MES 8 | L3: MES 9 | M3: MES 10 | N3: MES 11 | O3: MES 12 | P3: TOTAL AÑO 1 | Q3: MEDIAS MENSUALES | S3: MES 1 | T3: MES 2 | U3: MES 3 | V3: MES 4 | W3: MES 5 | X3: MES 6 | Y3: MES 7 | Z3: MES 8 | AA3: MES 9 | AB3: MES 10 | AC3: MES 11 | AD3: MES 12 | AE3: TOTAL AÑO 2 | AF3: MEDIAS MENSUALES
B4: PRODUCTO / SERVICIO 1 | C4: UNIDADES VENDIDAS | J4: 30 | K4: 30 | L4: 30 | M4: 30 | N4: 30 | O4: 30 | P4: =SUM(D4:O4) -> 180 | Q4: =P4/12 -> 15 | S4: 35 | T4: 35 | U4: 40 | V4: 40 | W4: 40 | X4: 50 | Y4: 50 | Z4: 60 | AA4: 60 | AB4: 60 | AC4: 60 | AD4: 60 | AE4: =SUM(S4:AD4) -> 590 | AF4: =AE4/12 -> 49.166667
B5: Suscripción Anual Web | C5: PRECIO MEDIO SIN IVA | D5: 0 | E5: =D5 -> 0 | F5: =E5 -> 0 | G5: =F5 -> 0 | H5: =G5 -> 0 | I5: =H5 -> 0 | J5: 41.32 | K5: =J5 -> 41.32 | L5: =K5 -> 41.32 | M5: =L5 -> 41.32 | N5: =M5 -> 41.32 | O5: =N5 -> 41.32 | P5: =J5 -> 41.32 | S5: 41.32 | T5: =S5 -> 41.32 | U5: =T5 -> 41.32 | V5: =U5 -> 41.32 | W5: =V5 -> 41.32 | X5: =W5 -> 41.32 | Y5: 41.32 | Z5: =Y5 -> 41.32 | AA5: =Z5 -> 41.32 | AB5: =AA5 -> 41.32 | AC5: =AB5 -> 41.32 | AD5: =AC5 -> 41.32 | AE5: =Y5 -> 41.32
C6: TOTAL VENTAS PRODUCTO 1 | D6: 0 | E6: 0 | F6: 0 | G6: 0 | H6: 0 | I6: 0 | J6: =J4*J5 -> 1239.6 | K6: =K4*K5 -> 1239.6 | L6: =L4*L5 -> 1239.6 | M6: =M4*M5 -> 1239.6 | N6: =N4*N5 -> 1239.6 | O6: =O4*O5 -> 1239.6 | P6: =SUM(D6:O6) -> 7437.6 | Q6: =P6/12 -> 619.8 | S6: =S4*S5 -> 1446.2 | T6: =T4*T5 -> 1446.2 | U6: =U4*U5 -> 1652.8 | V6: =V4*V5 -> 1652.8 | W6: =W4*W5 -> 1652.8 | X6: =X4*X5 -> 2066 | Y6: =Y4*Y5 -> 2066 | Z6: =Z4*Z5 -> 2479.2 | ... AD6: =AD4*AD5 -> 2479.2 | AE6: =SUM(S6:AD6) -> 24378.8 | AF6: =AE6/12 -> 2031.5667
C8: TOTAL INGRESOS SIN IVA | D8: 0 | E8: 0 | F8: 0 | G8: 0 | H8: 0 | I8: 0 | J8: =J6 -> 1239.6 | K8: =K6 -> 1239.6 | L8: =L6 -> 1239.6 | M8: =M6 -> 1239.6 | N8: =N6 -> 1239.6 | O8: =O6 -> 1239.6 | P8: =P6 -> 7437.6 | S8: TOTAL INGRESOS SIN IVA | T8: =T6 -> 1446.2 | U8: =U6 -> 1652.8 | V8: =V6 -> 1652.8 | W8: =W6 -> 1652.8 | X8: =X6 -> 2066 | Y8: =Y6 -> 2066 | Z8: =Z6 -> 2479.2 | AA8: =AA6 -> 2479.2 | ... AF8: =AF6 -> 2031.5667
C9: IMPORTE IVA 21% | D9: =D8*21% -> 0 | E9: =E8*21% -> 0 | F9: =F8*21% -> 0 | G9: =G8*21% -> 0 | H9: =H8*21% -> 0 | I9: =I8*21% -> 0 | J9: =J8*21% -> 260.316 | K9: =K8*21% -> 260.316 | ... P9: =P8*21% -> 1561.896 | S9: IMPORTE IVA 21% | T9: =T8*21% -> 303.702 | U9: =U8*21% -> 347.088 | V9: =V8*21% -> 347.088 | W9: =W8*21% -> 347.088 | X9: =X8*21% -> 433.86 | Y9: =Y8*21% -> 433.86 | Z9: =Z8*21% -> 520.632 | AA9: =AA8*21% -> 520.632 | ... AF9: =AF8*21% -> 426.629
C10: TOTAL INGRESOS CON IVA | D10: =SUM(D8:D9) -> 0 | E10: =SUM(E8:E9) -> 0 | F10: =SUM(F8:F9) -> 0 | G10: =SUM(G8:G9) -> 0 | H10: =SUM(H8:H9) -> 0 | I10: =SUM(I8:I9) -> 0 | J10: =SUM(J8:J9) -> 1499.916 | K10: =SUM(K8:K9) -> 1499.916 | ... P10: =SUM(P8:P9) -> 8999.496 | S10: TOTAL INGRESOS CON IVA | T10: =SUM(T8:T9) -> 1749.902 | U10: =SUM(U8:U9) -> 1999.888 | V10: =SUM(V8:V9) -> 1999.888 | W10: =SUM(W8:W9) -> 1999.888 | X10: =SUM(X8:X9) -> 2499.86 | Y10: =SUM(Y8:Y9) -> 2499.86 | Z10: =SUM(Z8:Z9) -> 2999.832 | AA10: =SUM(AA8:AA9) -> 2999.832 | ... AF10: =SUM(AF8:AF9) -> 2458.1957

Sheet CUENTA_DE_RESULTADOS_o_PyG
C1: PREVISIÓN ECONÓMICO-FINANCIERA "ESTEL"
C3: CUENTA DE RESULTADOS
D5: PREVISIÓN AÑO 1 | F5: PREVISIÓN AÑO 2 | G5: PREVISIÓN AÑO 3
C7: INGRESOS TOTALES | D7: =INGRESOS!P8 -> 7437.6 | F7: =SUM(F8) -> 24378.8 | G7: =SUM(G8) -> 32911.38
C8: Ingresos por Suscripción Anual Web | D8: =INGRESOS!P6 -> 7437.6 | F8: =INGRESOS!AE8 -> 24378.8 | G8: =F8+(F8*35%) -> 32911.38
C10: GASTOS TOTALES | D10: =SUM(D11:D13) -> 22205 | F10: =SUM(F11:F12) -> 21677.5 | G10: =SUM(G11:G12) -> 22709.5
C11: Costes fijos | D11: =COSTES_FIJOS!D20 -> 20640 | F11: =D11+(D11*5%) -> 21672 | G11: =D11+(D11*10%) -> 22704
C12: Costes variables | D12: =COSTES_VARIABLES!E9*INGRESOS!P4 -> 990 | F12: =COSTES_VARIABLES!E9 -> 5.5 | G12: =COSTES_VARIABLES!E9 -> 5.5
C13: Gastos de puesta en marcha | D13: =GASTOS_DE_PUESTA_EN_MARCHA!C19 -> 575 | F13: 0 | G13: 0
C15: BENEFICIO ANTES DE IMPUESTOS, AMORTIZACIONES Y GASTOS FINANCIEROS (EBITDA) | D15: =D7-D10 -> -14767.4 | F15: =F7-F10 -> 2701.3 | G15: =G7-G10 -> 10201.88
C17: AMORTIZACIONES | D17: ='INVERSIÓN_EN_INMOVILIZADO'!E7 -> 0 | F17: =D17 -> 0 | G17: =D17 -> 0
C19: BENEFICIO ANTES DE IMPUESTOS Y GASTOS FINANCIEROS (EBIT) | D19: =D15-D17 -> -14767.4 | F19: =F15-F17 -> 2701.3 | G19: =G15-G17 -> 10201.88
C21: GASTOS FINANCIEROS | D21: 0 | F21: 0 | G21: 0
C23: BENEFICIO ANTES DE IMPUESTOS | D23: =D19-D21 -> -14767.4 | F23: =F19-F21 -> 2701.3 | G23: =G19-G21 -> 10201.88
C25: PAGOS A CUENTA IRPF (MODELO 130) | D25: 0 | F25: =F23*20% -> 540.26 | G25: =G23*20% -> 2040.376
C27: EXCEDENTE NETO DISPONIBLE | D27: =D23-D25 -> -14767.4 | F27: =F23-F25 -> 2161.04 | G27: =G23-G25 -> 8161.504
C29: REINVERSIÓN EN LA EMPRESA | D29: =D27 -> -14767.4 | F29: =F27*40% -> 864.416 | G29: =G27*40% -> 3264.6016
C30: REPARTO DE BENEFICIOS ENTRE LOS SOCIOS | D30: 0 | F30: =F27*60% -> 1296.624 | G30: =G27*60% -> 4896.9024
